webhook/__init__.py
webhook/logging.py
webhook/webhook_manager.py
webhook/webhook_sender.py
Simple_Webhooks-1.0.0.dist-info/METADATA
Simple_Webhooks-1.0.0.dist-info/WHEEL
Simple_Webhooks-1.0.0.dist-info/top_level.txt
Simple_Webhooks-1.0.0.dist-info/RECORD
