Metadata-Version: 2.1
Name: Simple-Webhooks
Version: 1.0.0
Summary: Lightweight and flexible Python Package to send webhooks
Author-email: Lev kany <levkany.dev@gmail.com>
License: MIT
Project-URL: Homepage, https://github.com/levkany/webhooks
Project-URL: Issues, https://github.com/levkany/webhooks/issues
Requires-Python: >=3.10
Requires-Dist: requests >=2.26.0
Requires-Dist: pytest >=8.1.1
